lorry_date/__init__.py
lorry_date/dateutils.py
tests/__init__.py
tests/test_dateutils.py
mydatepackage-0.1.0.dist-info/LICENSE
mydatepackage-0.1.0.dist-info/METADATA
mydatepackage-0.1.0.dist-info/WHEEL
mydatepackage-0.1.0.dist-info/top_level.txt
mydatepackage-0.1.0.dist-info/RECORD
